{
  "as_of": "2026-06-30 20:20 UTC",
  "macro": {
    "spx": null,
    "ten_year": {
      "yield_pct": 4.38,
      "delta_bp_1d": 0.0
    },
    "mortgage_30y": {
      "rate_pct": 6.49,
      "delta_bp_wow": 2.000000000000046
    },
    "starts": {
      "level_saar": 1177.0,
      "mom": -0.15445402298850575
    }
  },
  "permits": {
    "florida": {
      "latest": 13055,
      "latest_date": "2026-05",
      "mom": -0.10557687037544528,
      "yoy": -0.1036116451524306,
      "ytd": -0.15488219982647,
      "ytd_count": 63312,
      "latest_year": 2026,
      "latest_month_name": "May"
    },
    "msa": {
      "Orlando–Kissimmee–Sanford": {
        "total": {
          "latest": 1846,
          "latest_year": 2026,
          "latest_month": 5,
          "latest_month_name": "May",
          "mom": -0.041536863966770476,
          "yoy": 0.030133928571428603,
          "ytd_yoy": -0.40573954742994156,
          "ytd_count": 7931
        },
        "one_unit": {
          "latest": 1050,
          "latest_year": 2026,
          "latest_month": 5,
          "latest_month_name": "May",
          "mom": -0.0658362989323843,
          "yoy": -0.13007456503728254,
          "ytd_yoy": -0.2376164424072157,
          "ytd_count": 5156
        },
        "dom": {
          "days": 70,
          "yoy": 0.07692307692307687,
          "as_of": "2026-05"
        }
      },
      "Tampa–St. Petersburg–Clearwater": {
        "total": {
          "latest": 2505,
          "latest_year": 2026,
          "latest_month": 5,
          "latest_month_name": "May",
          "mom": 0.5666041275797373,
          "yoy": 0.03256389117889524,
          "ytd_yoy": -0.0788973384030418,
          "ytd_count": 8721
        },
        "one_unit": {
          "latest": 1141,
          "latest_year": 2026,
          "latest_month": 5,
          "latest_month_name": "May",
          "mom": -0.047579298831385675,
          "yoy": -0.14595808383233533,
          "ytd_yoy": -0.005497337227280519,
          "ytd_count": 5789
        },
        "dom": {
          "days": 67,
          "yoy": 0.1166666666666667,
          "as_of": "2026-05"
        }
      },
      "Ocala": {
        "total": {
          "latest": 481,
          "latest_year": 2026,
          "latest_month": 5,
          "latest_month_name": "May",
          "mom": -0.1819727891156463,
          "yoy": -0.034136546184738936,
          "ytd_yoy": -0.02604166666666663,
          "ytd_count": 2805
        },
        "one_unit": {
          "latest": 477,
          "latest_year": 2026,
          "latest_month": 5,
          "latest_month_name": "May",
          "mom": -0.18877551020408168,
          "yoy": -0.01851851851851849,
          "ytd_yoy": 0.02792256142963523,
          "ytd_count": 2761
        },
        "dom": {
          "days": 79,
          "yoy": 0.09722222222222232,
          "as_of": "2026-05"
        }
      },
      "Palm Bay–Melbourne–Titusville": {
        "total": {
          "latest": 328,
          "latest_year": 2026,
          "latest_month": 5,
          "latest_month_name": "May",
          "mom": 0.08250825082508251,
          "yoy": 0.2615384615384615,
          "ytd_yoy": -0.10857142857142854,
          "ytd_count": 1404
        },
        "one_unit": {
          "latest": 328,
          "latest_year": 2026,
          "latest_month": 5,
          "latest_month_name": "May",
          "mom": 0.08250825082508251,
          "yoy": 0.3015873015873016,
          "ytd_yoy": 0.010799136069114423,
          "ytd_count": 1404
        },
        "dom": {
          "days": 65,
          "yoy": 0.0,
          "as_of": "2026-05"
        }
      }
    }
  },
  "watchlist": [],
  "feed": [
    {
      "title": "Trump calls 21st Century ROAD to Housing Act ‘a yawn’",
      "link": "https://www.housingwire.com/articles/trump-calls-21st-century-road-to-housing-act-a-yawn/",
      "published": "Tue, 30 Jun 2026"
    },
    {
      "title": "Why Fed President Beth Hammack wants more rate hikes",
      "link": "https://www.housingwire.com/articles/fed-president-beth-hammack-more-rate-hikes/",
      "published": "Tue, 30 Jun 2026"
    },
    {
      "title": "MRED seeks arbitration in Zillow antitrust lawsuit",
      "link": "https://www.housingwire.com/articles/mred-compel-arbitration-zillow/",
      "published": "Tue, 30 Jun 2026"
    },
    {
      "title": "Bipartisan bill would allocate CDBG funds to disaster prevention efforts",
      "link": "https://www.housingwire.com/articles/liccardo-timmons-bill-ounce-of-prevention-act/",
      "published": "Tue, 30 Jun 2026"
    },
    {
      "title": "CRMLS adds ‘Limited Exposure Coming Soon’ listing option",
      "link": "https://www.housingwire.com/articles/crmls-limited-exposure-coming-soon/",
      "published": "Tue, 30 Jun 2026"
    },
    {
      "title": "Non-QM originations on pace for new post-crisis record in 2026",
      "link": "https://www.housingwire.com/articles/non-qm-originations-175b-2026/",
      "published": "Tue, 30 Jun 2026"
    },
    {
      "title": "Seller Choice Keeps Winning, Quietly",
      "link": "https://www.redfin.com/news/seller-choice-keeps-winning-quietly/",
      "published": "Tue, 30 Jun 2026"
    },
    {
      "title": "A Tale of Two Markets: Luxury Home Prices Are Rising 3 Times Faster Than Non-Luxury Prices",
      "link": "https://www.redfin.com/news/luxury-housing-market-may-2026/",
      "published": "Tue, 30 Jun 2026"
    },
    {
      "title": "19% of of House Hunters Are Looking to Relocate–And They’re Headed to the Sun Belt",
      "link": "https://www.redfin.com/news/migration-q1-2026/",
      "published": "Mon, 29 Jun 2026"
    },
    {
      "title": "Gen Z Is Creating A New Path To Prosperity",
      "link": "https://www.redfin.com/news/gen-z-path-to-prosperity/",
      "published": "Fri, 26 Jun 2026"
    },
    {
      "title": "Americans Across Party Lines Back Policies to Improve Housing Affordability: Redfin Survey",
      "link": "https://www.redfin.com/news/survey-americans-support-housing-policy/",
      "published": "Fri, 26 Jun 2026"
    },
    {
      "title": "Fewer Homeowners Are Listing as Spring Market Ends With a Whimper, Not a Bang",
      "link": "https://www.redfin.com/news/housing-market-update-new-listings-decline-spring-2026/",
      "published": "Thu, 25 Jun 2026"
    }
  ],
  "feed_101020": {
    "macro": [
      {
        "title": "Why Fed President Beth Hammack wants more rate hikes",
        "url": "https://www.housingwire.com/articles/fed-president-beth-hammack-more-rate-hikes/",
        "what": "Oil is near $70, but Fed hawks cite sticky inflation and full employment, keeping rate hikes in play and mortgage rates from falling.",
        "numbers": "$70,",
        "justified": "housingwire.com — https://www.housingwire.com/articles/fed-president-beth-hammack-more-rate-hikes/",
        "why": "Rates & inflation shape discount rates and housing affordability.",
        "market": "Lower rates support demand/valuations; higher rates pressure builders/REITs and slow transactions."
      },
      {
        "title": "A Tale of Two Markets: Luxury Home Prices Are Rising 3 Times Faster Than Non-Luxury Prices",
        "url": "https://www.redfin.com/news/luxury-housing-market-may-2026/",
        "what": "Luxury U.S",
        "numbers": "4.7, 1.5, 3",
        "justified": "redfin.com — https://www.redfin.com/news/luxury-housing-market-may-2026/",
        "why": "Rates & inflation shape discount rates and housing affordability.",
        "market": "Lower rates support demand/valuations; higher rates pressure builders/REITs and slow transactions."
      },
      {
        "title": "Americans Across Party Lines Back Policies to Improve Housing Affordability: Redfin Survey",
        "url": "https://www.redfin.com/news/survey-americans-support-housing-policy/",
        "what": "Most Republicans and Democrats believe there should be federal policies in place to make housing more affordable, according to a recent Redfin survey",
        "numbers": "85, 77",
        "justified": "redfin.com — https://www.redfin.com/news/survey-americans-support-housing-policy/",
        "why": "Rates & inflation shape discount rates and housing affordability.",
        "market": "Lower rates support demand/valuations; higher rates pressure builders/REITs and slow transactions."
      }
    ],
    "housing": [
      {
        "title": "Trump calls 21st Century ROAD to Housing Act ‘a yawn’",
        "url": "https://www.housingwire.com/articles/trump-calls-21st-century-road-to-housing-act-a-yawn/",
        "what": "The comments came as Trump reinforced prioritization of the Safeguard American Voter Eligibility (SAVE) Act as his top domestic priority.",
        "numbers": "",
        "justified": "housingwire.com — https://www.housingwire.com/articles/trump-calls-21st-century-road-to-housing-act-a-yawn/",
        "why": "Inventory and velocity drive pricing power and volume.",
        "market": "Rising inventory/DOM tilts to buyers; tight supply supports prices."
      },
      {
        "title": "MRED seeks arbitration in Zillow antitrust lawsuit",
        "url": "https://www.housingwire.com/articles/mred-compel-arbitration-zillow/",
        "what": "MRED asked the court to compel arbitration with Zillow and stay claims ahead of a 2 day hearing on a preliminary injunction motion.",
        "numbers": "2",
        "justified": "housingwire.com — https://www.housingwire.com/articles/mred-compel-arbitration-zillow/",
        "why": "Relevant development for housing and markets.",
        "market": "Watch second-order effects across builders, lenders, and REITs."
      },
      {
        "title": "CRMLS adds ‘Limited Exposure Coming Soon’ listing option",
        "url": "https://www.housingwire.com/articles/crmls-limited-exposure-coming-soon/",
        "what": "CRMLS launched 'Limited Exposure Coming Soon' listings, letting sellers set Internet display to No and exclude listings from IDX feeds.",
        "numbers": "",
        "justified": "housingwire.com — https://www.housingwire.com/articles/crmls-limited-exposure-coming-soon/",
        "why": "Inventory and velocity drive pricing power and volume.",
        "market": "Rising inventory/DOM tilts to buyers; tight supply supports prices."
      },
      {
        "title": "Joe Rath: Rocket Redfin integration gains momentum one year after $1.75B deal",
        "url": "https://www.housingwire.com/articles/rocket-redfin-integration-early-access/",
        "what": "Rocket says Redfin integration is ahead of plan after the $1.75B deal, citing 75% of sellers would move if friction fell.",
        "numbers": "$1.75, 75",
        "justified": "housingwire.com — https://www.housingwire.com/articles/rocket-redfin-integration-early-access/",
        "why": "Relevant development for housing and markets.",
        "market": "Watch second-order effects across builders, lenders, and REITs."
      },
      {
        "title": "Seller Choice Keeps Winning, Quietly",
        "url": "https://www.redfin.com/news/seller-choice-keeps-winning-quietly/",
        "what": "CRMLS, the largest real estate listing service in the country, just gave home sellers a more flexible way to bring their home to the market before it is broadly launched across the internet",
        "numbers": "",
        "justified": "redfin.com — https://www.redfin.com/news/seller-choice-keeps-winning-quietly/",
        "why": "Inventory and velocity drive pricing power and volume.",
        "market": "Rising inventory/DOM tilts to buyers; tight supply supports prices."
      },
      {
        "title": "19% of of House Hunters Are Looking to Relocate–And They’re Headed to the Sun Belt",
        "url": "https://www.redfin.com/news/migration-q1-2026/",
        "what": "Nearly 1 in 5 U.S",
        "numbers": "1, 5, 19",
        "justified": "redfin.com — https://www.redfin.com/news/migration-q1-2026/",
        "why": "Rent moves feed shelter inflation and multifamily fundamentals.",
        "market": "Rising rents help MF REITs; falling rents ease inflation but pressure NOI."
      },
      {
        "title": "Gen Z Is Creating A New Path To Prosperity",
        "url": "https://www.redfin.com/news/gen-z-path-to-prosperity/",
        "what": "This piece was originally published on Forbes on June 8, 2026",
        "numbers": "8,, 2026., 70",
        "justified": "redfin.com — https://www.redfin.com/news/gen-z-path-to-prosperity/",
        "why": "Rates & inflation shape discount rates and housing affordability.",
        "market": "Lower rates support demand/valuations; higher rates pressure builders/REITs and slow transactions."
      },
      {
        "title": "Fewer Homeowners Are Listing as Spring Market Ends With a Whimper, Not a Bang",
        "url": "https://www.redfin.com/news/housing-market-update-new-listings-decline-spring-2026/",
        "what": "The median U.S",
        "numbers": "1.7, 21, 0.4",
        "justified": "redfin.com — https://www.redfin.com/news/housing-market-update-new-listings-decline-spring-2026/",
        "why": "Price trend signals wealth effects and buyer/seller power.",
        "market": "Firm prices help builder margins; softness hits comps and sentiment."
      }
    ],
    "notables": [
      {
        "title": "Bipartisan bill would allocate CDBG funds to disaster prevention efforts",
        "url": "https://www.housingwire.com/articles/liccardo-timmons-bill-ounce-of-prevention-act/",
        "what": "Reps",
        "numbers": "",
        "justified": "housingwire.com — https://www.housingwire.com/articles/liccardo-timmons-bill-ounce-of-prevention-act/",
        "why": "Relevant development for housing and markets.",
        "market": "Watch second-order effects across builders, lenders, and REITs."
      },
      {
        "title": "Non-QM originations on pace for new post-crisis record in 2026",
        "url": "https://www.housingwire.com/articles/non-qm-originations-175b-2026/",
        "what": "Non-QM production is expected to reach $175 billion in 2026, compared to $108 billion in 2025.",
        "numbers": "$175 billion, 2026,, $108 billion, 2025.",
        "justified": "housingwire.com — https://www.housingwire.com/articles/non-qm-originations-175b-2026/",
        "why": "Relevant development for housing and markets.",
        "market": "Watch second-order effects across builders, lenders, and REITs."
      },
      {
        "title": "Portside Real Estate Group adds agent Heather Szela in central Maine",
        "url": "https://www.housingwire.com/articles/portside-real-estate-group-adds-agent-heather-szela-in-central-maine/",
        "what": "A LeadingRE affiliate, Portside Real Estate Group reported $1.33 billion in 2025 volume across 2,090 transaction sides.",
        "numbers": "$1.33 billion, 2025, 2,090",
        "justified": "housingwire.com — https://www.housingwire.com/articles/portside-real-estate-group-adds-agent-heather-szela-in-central-maine/",
        "why": "Relevant development for housing and markets.",
        "market": "Watch second-order effects across builders, lenders, and REITs."
      },
      {
        "title": "Dovenmuehle names Ann Morey head of product",
        "url": "https://www.housingwire.com/articles/dovenmuehle-appoints-ann-morey/",
        "what": "Dovenmuehle appointed Ann Morey as head of product, tasking her with product vision, road maps and team leadership.",
        "numbers": "",
        "justified": "housingwire.com — https://www.housingwire.com/articles/dovenmuehle-appoints-ann-morey/",
        "why": "Relevant development for housing and markets.",
        "market": "Watch second-order effects across builders, lenders, and REITs."
      },
      {
        "title": "Figure CEO says $300M prefunded securitization gives ‘added certainty’ to originators",
        "url": "https://www.housingwire.com/articles/figure-prefunded-securitization-connect/",
        "what": "Figure closed a $300 million prefunded securitization for Figure Connect loans, with investors committing capital before origination.",
        "numbers": "$300 million",
        "justified": "housingwire.com — https://www.housingwire.com/articles/figure-prefunded-securitization-connect/",
        "why": "Relevant development for housing and markets.",
        "market": "Watch second-order effects across builders, lenders, and REITs."
      }
    ]
  }
}