{
  "as_of": "2026-06-26 01:29 UTC",
  "macro": {
    "spx": null,
    "ten_year": {
      "yield_pct": 4.41,
      "delta_bp_1d": -8.999999999999986
    },
    "mortgage_30y": {
      "rate_pct": 6.49,
      "delta_bp_wow": 2.000000000000046
    },
    "starts": {
      "level_saar": 1177.0,
      "mom": -0.15445402298850575
    }
  },
  "permits": {
    "florida": {
      "latest": 13055,
      "latest_date": "2026-05",
      "mom": -0.10557687037544528,
      "yoy": -0.1036116451524306,
      "ytd": -0.15488219982647,
      "ytd_count": 63312,
      "latest_year": 2026,
      "latest_month_name": "May"
    },
    "msa": {
      "Orlando–Kissimmee–Sanford": {
        "total": {
          "latest": 1846,
          "latest_year": 2026,
          "latest_month": 5,
          "latest_month_name": "May",
          "mom": -0.041536863966770476,
          "yoy": 0.030133928571428603,
          "ytd_yoy": -0.40573954742994156,
          "ytd_count": 7931
        },
        "one_unit": {
          "latest": 1050,
          "latest_year": 2026,
          "latest_month": 5,
          "latest_month_name": "May",
          "mom": -0.0658362989323843,
          "yoy": -0.13007456503728254,
          "ytd_yoy": -0.2376164424072157,
          "ytd_count": 5156
        },
        "dom": {
          "days": 70,
          "yoy": 0.07692307692307687,
          "as_of": "2026-05"
        }
      },
      "Tampa–St. Petersburg–Clearwater": {
        "total": {
          "latest": 2505,
          "latest_year": 2026,
          "latest_month": 5,
          "latest_month_name": "May",
          "mom": 0.5666041275797373,
          "yoy": 0.03256389117889524,
          "ytd_yoy": -0.0788973384030418,
          "ytd_count": 8721
        },
        "one_unit": {
          "latest": 1141,
          "latest_year": 2026,
          "latest_month": 5,
          "latest_month_name": "May",
          "mom": -0.047579298831385675,
          "yoy": -0.14595808383233533,
          "ytd_yoy": -0.005497337227280519,
          "ytd_count": 5789
        },
        "dom": {
          "days": 67,
          "yoy": 0.1166666666666667,
          "as_of": "2026-05"
        }
      },
      "Ocala": {
        "total": {
          "latest": 481,
          "latest_year": 2026,
          "latest_month": 5,
          "latest_month_name": "May",
          "mom": -0.1819727891156463,
          "yoy": -0.034136546184738936,
          "ytd_yoy": -0.02604166666666663,
          "ytd_count": 2805
        },
        "one_unit": {
          "latest": 477,
          "latest_year": 2026,
          "latest_month": 5,
          "latest_month_name": "May",
          "mom": -0.18877551020408168,
          "yoy": -0.01851851851851849,
          "ytd_yoy": 0.02792256142963523,
          "ytd_count": 2761
        },
        "dom": {
          "days": 79,
          "yoy": 0.09722222222222232,
          "as_of": "2026-05"
        }
      },
      "Palm Bay–Melbourne–Titusville": {
        "total": {
          "latest": 328,
          "latest_year": 2026,
          "latest_month": 5,
          "latest_month_name": "May",
          "mom": 0.08250825082508251,
          "yoy": 0.2615384615384615,
          "ytd_yoy": -0.10857142857142854,
          "ytd_count": 1404
        },
        "one_unit": {
          "latest": 328,
          "latest_year": 2026,
          "latest_month": 5,
          "latest_month_name": "May",
          "mom": 0.08250825082508251,
          "yoy": 0.3015873015873016,
          "ytd_yoy": 0.010799136069114423,
          "ytd_count": 1404
        },
        "dom": {
          "days": 65,
          "yoy": 0.0,
          "as_of": "2026-05"
        }
      }
    }
  },
  "watchlist": [],
  "feed": [
    {
      "title": "KB Home Q2 2026 earnings point to scale vs execution debate",
      "link": "https://www.housingwire.com/articles/kb-home-built-to-order-shift/",
      "published": "Thu, 25 Jun 2026"
    },
    {
      "title": "Experienced Realtors hold the line in a tough housing market",
      "link": "https://www.housingwire.com/articles/nar-2026-member-profile-experience/",
      "published": "Thu, 25 Jun 2026"
    },
    {
      "title": "Senators push bipartisan plan to ‘save Social Security’",
      "link": "https://www.housingwire.com/articles/bipartisan-plan-to-save-social-security/",
      "published": "Thu, 25 Jun 2026"
    },
    {
      "title": "Young buyers are priced out in most U.S. metros, Pew data shows",
      "link": "https://www.housingwire.com/articles/young-homebuyers-priced-out-most-us-metros-pew-2026/",
      "published": "Thu, 25 Jun 2026"
    },
    {
      "title": "JPMorgan Chase names co-presidents as Dimon succession plan takes shape",
      "link": "https://www.housingwire.com/articles/jpmorgan-petno-rohrbaugh-co-presidents/",
      "published": "Thu, 25 Jun 2026"
    },
    {
      "title": "CoStar stockholders back directors, approve pay plan",
      "link": "https://www.housingwire.com/articles/costar-directors-pay-vote/",
      "published": "Thu, 25 Jun 2026"
    },
    {
      "title": "Fewer Homeowners Are Listing as Spring Market Ends With a Whimper, Not a Bang",
      "link": "https://www.redfin.com/news/housing-market-update-new-listings-decline-spring-2026/",
      "published": "Thu, 25 Jun 2026"
    },
    {
      "title": "Congress Takes Historic Step on Housing Affordability with Bipartisan ROAD to Housing Act",
      "link": "https://www.redfin.com/news/road-to-housing-act-historic/",
      "published": "Wed, 24 Jun 2026"
    },
    {
      "title": "Flood-Prone Parts of America Are Losing Residents at Nearly Twice Last Year’s Rate",
      "link": "https://www.redfin.com/news/climate-migration-real-estate-2026/",
      "published": "Wed, 24 Jun 2026"
    },
    {
      "title": "NYC Suburbs and the Bay Area Are This Spring’s Most Competitive Housing Markets",
      "link": "https://www.redfin.com/news/most-competitive-housing-markets-2026/",
      "published": "Tue, 23 Jun 2026"
    },
    {
      "title": "U.S. Home-Price Growth Accelerated in May, Fueled by April’s Brief Mortgage-Rate Reprieve",
      "link": "https://www.redfin.com/news/home-price-index-may-2026/",
      "published": "Tue, 23 Jun 2026"
    },
    {
      "title": "46% of Home Sellers Gave Concessions to Buyers in May, the Highest Share on Record For That Month",
      "link": "https://www.redfin.com/news/home-seller-concessions-record-high-rate/",
      "published": "Mon, 22 Jun 2026"
    }
  ],
  "feed_101020": {
    "macro": [
      {
        "title": "Young buyers are priced out in most U.S. metros, Pew data shows",
        "url": "https://www.housingwire.com/articles/young-homebuyers-priced-out-most-us-metros-pew-2026/",
        "what": "Buying a first home has gotten materially harder for young adults in most major U.S",
        "numbers": "2019,",
        "justified": "housingwire.com — https://www.housingwire.com/articles/young-homebuyers-priced-out-most-us-metros-pew-2026/",
        "why": "Rates & inflation shape discount rates and housing affordability.",
        "market": "Lower rates support demand/valuations; higher rates pressure builders/REITs and slow transactions."
      },
      {
        "title": "Mortgage payments rise 2.2% in May as rates, loan sizes grow",
        "url": "https://www.housingwire.com/articles/mba-papi-rises-may/",
        "what": "MBA's PAPI rose 2.2% to a reading of 159.4 in May as median purchase payments increased to $2,198 due to higher rates and loan sizes.",
        "numbers": "2.2, 159.4, $2,198",
        "justified": "housingwire.com — https://www.housingwire.com/articles/mba-papi-rises-may/",
        "why": "Rates & inflation shape discount rates and housing affordability.",
        "market": "Lower rates support demand/valuations; higher rates pressure builders/REITs and slow transactions."
      }
    ],
    "housing": [
      {
        "title": "Experienced Realtors hold the line in a tough housing market",
        "url": "https://www.housingwire.com/articles/nar-2026-member-profile-experience/",
        "what": "NAR 2026 Member Profile shows 13 years experience, nine sides in 2025, and affordability as the top buyer constraint at 27%.",
        "numbers": "2026, 13, 2025,, 27",
        "justified": "housingwire.com — https://www.housingwire.com/articles/nar-2026-member-profile-experience/",
        "why": "Relevant development for housing and markets.",
        "market": "Watch second-order effects across builders, lenders, and REITs."
      },
      {
        "title": "Fewer Homeowners Are Listing as Spring Market Ends With a Whimper, Not a Bang",
        "url": "https://www.redfin.com/news/housing-market-update-new-listings-decline-spring-2026/",
        "what": "The median U.S",
        "numbers": "1.7, 21, 0.4",
        "justified": "redfin.com — https://www.redfin.com/news/housing-market-update-new-listings-decline-spring-2026/",
        "why": "Price trend signals wealth effects and buyer/seller power.",
        "market": "Firm prices help builder margins; softness hits comps and sentiment."
      },
      {
        "title": "Congress Takes Historic Step on Housing Affordability with Bipartisan ROAD to Housing Act",
        "url": "https://www.redfin.com/news/road-to-housing-act-historic/",
        "what": "Passed unanimously out of the Senate Banking Committee, the ROAD to Housing Act embraces solutions to the housing affordability crisis like zoning reform and streamlining rules to encourage more homebuilding",
        "numbers": "",
        "justified": "redfin.com — https://www.redfin.com/news/road-to-housing-act-historic/",
        "why": "Relevant development for housing and markets.",
        "market": "Watch second-order effects across builders, lenders, and REITs."
      },
      {
        "title": "Flood-Prone Parts of America Are Losing Residents at Nearly Twice Last Year’s Rate",
        "url": "https://www.redfin.com/news/climate-migration-real-estate-2026/",
        "what": "High-flood-risk U.S",
        "numbers": "63,000, 2025, 70,000",
        "justified": "redfin.com — https://www.redfin.com/news/climate-migration-real-estate-2026/",
        "why": "Rates & inflation shape discount rates and housing affordability.",
        "market": "Lower rates support demand/valuations; higher rates pressure builders/REITs and slow transactions."
      },
      {
        "title": "NYC Suburbs and the Bay Area Are This Spring’s Most Competitive Housing Markets",
        "url": "https://www.redfin.com/news/most-competitive-housing-markets-2026/",
        "what": "More than half of homes are selling above asking price in Newark, San Francisco, San Jose and Nassau County, making them the most competitive markets in the nation",
        "numbers": "",
        "justified": "redfin.com — https://www.redfin.com/news/most-competitive-housing-markets-2026/",
        "why": "Price trend signals wealth effects and buyer/seller power.",
        "market": "Firm prices help builder margins; softness hits comps and sentiment."
      },
      {
        "title": "U.S. Home-Price Growth Accelerated in May, Fueled by April’s Brief Mortgage-Rate Reprieve",
        "url": "https://www.redfin.com/news/home-price-index-may-2026/",
        "what": "Home prices rose 0.3% month over month on a seasonally adjusted basis",
        "numbers": "0.3, 2.5, 29",
        "justified": "redfin.com — https://www.redfin.com/news/home-price-index-may-2026/",
        "why": "Rates & inflation shape discount rates and housing affordability.",
        "market": "Lower rates support demand/valuations; higher rates pressure builders/REITs and slow transactions."
      },
      {
        "title": "46% of Home Sellers Gave Concessions to Buyers in May, the Highest Share on Record For That Month",
        "url": "https://www.redfin.com/news/home-seller-concessions-record-high-rate/",
        "what": "Nearly half of U.S",
        "numbers": "46",
        "justified": "redfin.com — https://www.redfin.com/news/home-seller-concessions-record-high-rate/",
        "why": "Relevant development for housing and markets.",
        "market": "Watch second-order effects across builders, lenders, and REITs."
      }
    ],
    "notables": [
      {
        "title": "KB Home Q2 2026 earnings point to scale vs execution debate",
        "url": "https://www.housingwire.com/articles/kb-home-built-to-order-shift/",
        "what": "Homebuilding’s mid-year public company earnings season is now looking through the prism of the back half of 2026",
        "numbers": "2026.",
        "justified": "housingwire.com — https://www.housingwire.com/articles/kb-home-built-to-order-shift/",
        "why": "Relevant development for housing and markets.",
        "market": "Watch second-order effects across builders, lenders, and REITs."
      },
      {
        "title": "Senators push bipartisan plan to ‘save Social Security’",
        "url": "https://www.housingwire.com/articles/bipartisan-plan-to-save-social-security/",
        "what": "Proposals come as policymakers and financial professionals warn of looming funding shortfalls and confusion about how the program works.",
        "numbers": "",
        "justified": "housingwire.com — https://www.housingwire.com/articles/bipartisan-plan-to-save-social-security/",
        "why": "Relevant development for housing and markets.",
        "market": "Watch second-order effects across builders, lenders, and REITs."
      },
      {
        "title": "JPMorgan Chase names co-presidents as Dimon succession plan takes shape",
        "url": "https://www.housingwire.com/articles/jpmorgan-petno-rohrbaugh-co-presidents/",
        "what": "JPMorgan Chase has named Doug Petno and Troy Rohrbaugh as co-presidents effective immediately",
        "numbers": "",
        "justified": "housingwire.com — https://www.housingwire.com/articles/jpmorgan-petno-rohrbaugh-co-presidents/",
        "why": "Relevant development for housing and markets.",
        "market": "Watch second-order effects across builders, lenders, and REITs."
      },
      {
        "title": "CoStar stockholders back directors, approve pay plan",
        "url": "https://www.housingwire.com/articles/costar-directors-pay-vote/",
        "what": "CoStar investors reelected eight directors with over 93% support and approved say-on-pay at 71.38% as margins stay in focus.",
        "numbers": "93, 71.38",
        "justified": "housingwire.com — https://www.housingwire.com/articles/costar-directors-pay-vote/",
        "why": "Relevant development for housing and markets.",
        "market": "Watch second-order effects across builders, lenders, and REITs."
      },
      {
        "title": "Qualia expands wire fraud protection platform for title and escrow",
        "url": "https://www.housingwire.com/articles/qualia-expands-wire-fraud-protection-platform-for-title-and-escrow/",
        "what": "Expanded features include evaluation of all wire types, including commission payments and agent disbursements.",
        "numbers": "",
        "justified": "housingwire.com — https://www.housingwire.com/articles/qualia-expands-wire-fraud-protection-platform-for-title-and-escrow/",
        "why": "Relevant development for housing and markets.",
        "market": "Watch second-order effects across builders, lenders, and REITs."
      },
      {
        "title": "HomeServices, Elliman notch legal wins in commission suit saga",
        "url": "https://www.housingwire.com/articles/lutz-case-stayed-tuccori-settlement/",
        "what": "Florida judge denied a preliminary injunction and paused the Lutz lawsuit while Tuccori court weighs opt-in settlement final approvals.",
        "numbers": "",
        "justified": "housingwire.com — https://www.housingwire.com/articles/lutz-case-stayed-tuccori-settlement/",
        "why": "Relevant development for housing and markets.",
        "market": "Watch second-order effects across builders, lenders, and REITs."
      },
      {
        "title": "Senate Democrats press CFPB’s Vought over mass deletion of records",
        "url": "https://www.housingwire.com/articles/senate-democrats-question-cfpb-mass-deletion-records/",
        "what": "Senate Democrats have accused Consumer Financial Protection Bureau acting director Russell Vought of stripping away key consumer protection resources and obscuring past enforcement",
        "numbers": "",
        "justified": "housingwire.com — https://www.housingwire.com/articles/senate-democrats-question-cfpb-mass-deletion-records/",
        "why": "Relevant development for housing and markets.",
        "market": "Watch second-order effects across builders, lenders, and REITs."
      }
    ]
  }
}